Metadata-Version: 2.1
Name: triangleCode
Version: 0.0.1
Summary: a very basic addition function
Home-page: https://github.com/saurabhpl/sampleCode
Author: Saurabh Pratap Singh
License: MIT
Platform: UNKNOWN
License-File: LICENSE.txt
